ringer/__init__.py
ringer/api_client.py
ringer/api_response.py
ringer/configuration.py
ringer/exceptions.py
ringer/py.typed
ringer/rest.py
ringer/api/__init__.py
ringer/api/cic_api.py
ringer/api/cnam_api.py
ringer/api/dnc_api.py
ringer/api/dno_api.py
ringer/api/local_routing_number_lrn_api.py
ringer/api/ror_api.py
ringer/api/stirshaken_api.py
ringer/models/__init__.py
ringer/models/cic_response.py
ringer/models/cicror_response.py
ringer/models/cnam_response.py
ringer/models/dnc_update_report_inner.py
ringer/models/dno_response.py
ringer/models/error.py
ringer/models/lrn_response.py
ringer/models/ror_response.py
ringer/models/stir_shaken_request.py
ringer/models/stir_shaken_response.py
ringer_telique-1.0.18.dist-info/METADATA
ringer_telique-1.0.18.dist-info/WHEEL
ringer_telique-1.0.18.dist-info/top_level.txt
ringer_telique-1.0.18.dist-info/RECORD
